gnu_libc_dash_docset_generator/__init__.py
gnu_libc_dash_docset_generator/main.py
gnu_libc_dash_docset_generator/py.typed
gnu_libc_dash_docset_generator/resources/icon.png
gnu_libc_dash_docset_generator-2026.1.25.dist-info/licenses/LICENSE
gnu_libc_dash_docset_generator-2026.1.25.dist-info/METADATA
gnu_libc_dash_docset_generator-2026.1.25.dist-info/WHEEL
gnu_libc_dash_docset_generator-2026.1.25.dist-info/entry_points.txt
gnu_libc_dash_docset_generator-2026.1.25.dist-info/top_level.txt
gnu_libc_dash_docset_generator-2026.1.25.dist-info/RECORD
