Metadata-Version: 2.4
Name: gnu_libc_dash_docset_generator
Version: 2026.1.25
Summary: Dash docset generator for GNU C Library
Author-email: Louie Shprung <lshprung@tutanota.com>
License-Expression: GPL-3.0-or-later
Project-URL: Homepage, https://github.com/lshprung/gnu-libc-dash-docset
Project-URL: Issues, https://github.com/lshprung/gnu-libc-dash-docset/issues
Classifier: Operating System :: OS Independent
Classifier: Programming Language :: Python :: 3
Requires-Python: >=3.10
License-File: LICENSE
Requires-Dist: dash_docset_builder>=2026.01.25
Dynamic: license-file
